optisherpa_agents/__init__.py
optisherpa_agents/economist/__init__.py
optisherpa_agents/economist/agent.py
optisherpa_agents/energy_analyst/__init__.py
optisherpa_agents/energy_analyst/agent.py
optisherpa_agents/geopolitical_expert/__init__.py
optisherpa_agents/geopolitical_expert/agent.py
optisherpa_agents/transportation_supply_chain_analyst/__init__.py
optisherpa_agents/transportation_supply_chain_analyst/agent.py
optisherpa_agents-0.0.5.dist-info/METADATA
optisherpa_agents-0.0.5.dist-info/WHEEL
optisherpa_agents-0.0.5.dist-info/RECORD
