Metadata-Version: 2.1
Name: optisherpa-agents
Version: 0.0.5
Summary: This is a python package for optisherpa, its a small collection of autonomous agents
License: Apache
Author: Sharabh Shukla
Author-email: sharabh2019@gmail.com
Requires-Python: >=3.10,<3.13
Classifier: License :: Other/Proprietary License
Classifier: Programming Language :: Python :: 3
Classifier: Programming Language :: Python :: 3.10
Classifier: Programming Language :: Python :: 3.11
Classifier: Programming Language :: Python :: 3.12
Requires-Dist: crewai (>=0.11.0,<0.12.0)
Requires-Dist: duckduckgo-search (>=5.0,<5.1)
